ragas_examples/README.md
ragas_examples/agent_evals/__init__.py
ragas_examples/agent_evals/agent.py
ragas_examples/agent_evals/evals.py
ragas_examples/prompt_evals/__init__.py
ragas_examples/prompt_evals/evals.py
ragas_examples/prompt_evals/prompt.py
ragas_examples/rag_eval/__init__.py
ragas_examples/rag_eval/evals.py
ragas_examples/rag_eval/rag.py
ragas_examples/workflow_eval/__init__.py
ragas_examples/workflow_eval/evals.py
ragas_examples/workflow_eval/workflow.py
ragas_experimental/__init__.py
ragas_experimental/_version.py
ragas_experimental/cli.py
ragas_experimental/dataset.py
ragas_experimental/exceptions.py
ragas_experimental/experiment.py
ragas_experimental/simulation.py
ragas_experimental/utils.py
ragas_experimental/backends/README.md
ragas_experimental/backends/__init__.py
ragas_experimental/backends/base.py
ragas_experimental/backends/gdrive_backend.py
ragas_experimental/backends/inmemory.py
ragas_experimental/backends/local_csv.py
ragas_experimental/backends/local_jsonl.py
ragas_experimental/backends/registry.py
ragas_experimental/backends/utils.py
ragas_experimental/embeddings/__init__.py
ragas_experimental/embeddings/base.py
ragas_experimental/embeddings/google.py
ragas_experimental/embeddings/huggingface.py
ragas_experimental/embeddings/litellm.py
ragas_experimental/embeddings/openai.py
ragas_experimental/embeddings/utils.py
ragas_experimental/llms/__init__.py
ragas_experimental/llms/base.py
ragas_experimental/llms/llm.py
ragas_experimental/metrics/__init__.py
ragas_experimental/metrics/base.py
ragas_experimental/metrics/decorator.py
ragas_experimental/metrics/discrete.py
ragas_experimental/metrics/numeric.py
ragas_experimental/metrics/ranking.py
ragas_experimental/metrics/result.py
ragas_experimental/prompt/__init__.py
ragas_experimental/prompt/base.py
ragas_experimental/prompt/dynamic_few_shot.py
ragas_experimental/tracing/__init__.py
ragas_experimental/tracing/langfuse.py
ragas_experimental/tracing/mlflow.py
ragas_experimental-0.3.1.dist-info/METADATA
ragas_experimental-0.3.1.dist-info/WHEEL
ragas_experimental-0.3.1.dist-info/entry_points.txt
ragas_experimental-0.3.1.dist-info/top_level.txt
ragas_experimental-0.3.1.dist-info/RECORD
